{
    "SERVER": {
        "base_url": "http://localhost",
        "port": 3001,
        "uiUrl": "https://d2jle9c6ls1lyf.cloudfront.net",
        "prefix": "/api"
    },
    "AUTH": {
		"secret": "$2b$08$j.hh7XJkhDOh.3Bx6UTL6e",
		"secure": false,
		"expiry": 1209600
	},
    "DB": {
		"url": "prod-mongodb.docdb.amazonaws.com:27017/project123",
		"user": "administrator",
        "password": "db_user_password",
        "ssl": true
    },
    "AWS": {
        "IAM_USER_KEY": null,
        "IAM_USER_SECRET": null,
        "BUCKET_NAME": "",
        "SIGNATURE_VERSION": "v4",
		"REGION": "us-east-2"
	},
	"LAMBDA": {
		"url": "https://rs9jwkaso6.execute-api.us-east-2.amazonaws.com/default/DataOutcome_calculation",
		"key": "lambda_key"
	}
}
